pfc_prime_number_or_not.py
pfc_prime_number_or_not-1.0.dist-info/METADATA
pfc_prime_number_or_not-1.0.dist-info/WHEEL
pfc_prime_number_or_not-1.0.dist-info/top_level.txt
pfc_prime_number_or_not-1.0.dist-info/RECORD
